TracListOfWikiPagesMacro-0.5.dist-info/METADATA
TracListOfWikiPagesMacro-0.5.dist-info/RECORD
TracListOfWikiPagesMacro-0.5.dist-info/WHEEL
TracListOfWikiPagesMacro-0.5.dist-info/entry_points.txt
TracListOfWikiPagesMacro-0.5.dist-info/top_level.txt
traclistofwikipages/__init__.py
traclistofwikipages/macro.py
traclistofwikipages/htdocs/style.css
