Metadata-Version: 2.1
Name: TracListOfWikiPagesMacro
Version: 0.5
Summary: ListOfWikiPagesMacro for Trac v0.12
Home-page: https://www.trac-hacks.org/wiki/ListOfWikiPagesMacro
Author: Martin Scharrer
Author-email: martin@scharrer-online.de
License: GPLv3
Keywords: trac list wiki page macro
Platform: UNKNOWN
Classifier: Framework :: Trac
Requires-Dist: TracAdvParseArgsPlugin (>=0.2)
